live_studio_open_service/__init__.py
live_studio_open_service/client.py
live_studio_open_service-0.1.0.dist-info/METADATA
live_studio_open_service-0.1.0.dist-info/WHEEL
live_studio_open_service-0.1.0.dist-info/top_level.txt
live_studio_open_service-0.1.0.dist-info/RECORD
