Metadata-Version: 2.4
Name: live_studio_open_service
Version: 0.1.0
Summary: A simple socket-based RPC client
Author-email: kanglibo <kanglibo@bytedance.com>
License: MIT
Requires-Python: >=3.7
